setup.py
frasco_bootstrap/__init__.py
frasco_bootstrap.egg-info/PKG-INFO
frasco_bootstrap.egg-info/SOURCES.txt
frasco_bootstrap.egg-info/dependency_links.txt
frasco_bootstrap.egg-info/not-zip-safe
frasco_bootstrap.egg-info/requires.txt
frasco_bootstrap.egg-info/top_level.txt
frasco_bootstrap/macros/dropdown.html
frasco_bootstrap/macros/form.html
frasco_bootstrap/macros/menu.html
frasco_bootstrap/macros/ui.html
frasco_bootstrap/templates/bootstrap_layout.html
frasco_bootstrap/templates/users/layout.html
frasco_bootstrap/templates/users/login.html
frasco_bootstrap/templates/users/reset_password.html
frasco_bootstrap/templates/users/send_reset_password.html
frasco_bootstrap/templates/users/signup.html