Metadata-Version: 1.0
Name: frasco-bootstrap
Version: 0.1.3
Summary: Bootstrap (frontend framework) integration for Frasco
Home-page: http://github.com/frascoweb/frasco-bootstrap
Author: Maxime Bouroumeau-Fuseau
Author-email: maxime.bouroumeau@gmail.com
License: MIT
Platform: any
